LICENSE.txt
MANIFEST.in
README.rst
setup.py
picraft/__init__.py
picraft/block.color
picraft/block.data
picraft/block.py
picraft/compat.py
picraft/connection.py
picraft/events.py
picraft/exc.py
picraft/player.py
picraft/render.py
picraft/vector.py
picraft/world.py
picraft.egg-info/PKG-INFO
picraft.egg-info/SOURCES.txt
picraft.egg-info/dependency_links.txt
picraft.egg-info/requires.txt
picraft.egg-info/top_level.txt