Metadata-Version: 1.1
Name: picraft
Version: 0.6
Summary: An alternate Python interface for Minecraft.
Home-page: http://picraft.readthedocs.org/
Author: Dave Jones
Author-email: dave@waveform.org.uk
License: BSD License
Keywords: raspberrypi,minecraft
Platform: ALL
Classifier: Development Status :: 4 - Beta
Classifier: Environment :: Console
Classifier: Environment :: X11 Applications
Classifier: Intended Audience :: Developers
Classifier: License :: OSI Approved :: BSD License
Classifier: Operating System :: POSIX :: Linux
Classifier: Operating System :: Microsoft :: Windows
Classifier: Programming Language :: Python :: 2.7
Classifier: Programming Language :: Python :: 3.2
Classifier: Programming Language :: Python :: 3.3
Classifier: Programming Language :: Python :: 3.4
Classifier: Topic :: Games/Entertainment
